LICENSE.md
README.md
pyproject.toml
src/spinplots/__init__.py
src/spinplots/cli.py
src/spinplots/io.py
src/spinplots/plot.py
src/spinplots/py.typed
src/spinplots/spin.py
src/spinplots/utils.py
src/spinplots.egg-info/PKG-INFO
src/spinplots.egg-info/SOURCES.txt
src/spinplots.egg-info/dependency_links.txt
src/spinplots.egg-info/entry_points.txt
src/spinplots.egg-info/requires.txt
src/spinplots.egg-info/top_level.txt
tests/test_cli.py
tests/test_plots.py
tests/test_spin.py
tests/test_utils.py
tests/tests_io.py